{"version":1,"resource":"file:///home/mik3y/projects/repos/synk/crates/ui/src/editor/mod.rs","entries":[{"id":"STMA.rs","timestamp":1708490366908},{"id":"Jxfs.rs","timestamp":1708490390358},{"id":"1wXQ.rs","timestamp":1708490419838},{"id":"k1dr.rs","timestamp":1708490466988},{"id":"nsgC.rs","timestamp":1708490565924},{"id":"nkJj.rs","timestamp":1708491407417},{"id":"3HyS.rs","timestamp":1708491422720},{"id":"egWO.rs","timestamp":1708491443003},{"id":"TdBz.rs","timestamp":1708491975933},{"id":"I2Te.rs","timestamp":1708491992393},{"id":"6DdH.rs","timestamp":1708492080882},{"id":"Fs9A.rs","source":"undoRedo.source","timestamp":1708492088986},{"id":"ufb9.rs","timestamp":1708492107362},{"id":"iw1v.rs","timestamp":1708492144526},{"id":"BoDp.rs","timestamp":1708492154699},{"id":"Vb7D.rs","timestamp":1708520061921},{"id":"wRCH.rs","timestamp":1708528386278},{"id":"k6UM.rs","timestamp":1708528399965},{"id":"j4Ja.rs","timestamp":1708528418252},{"id":"gTS2.rs","timestamp":1708528429438},{"id":"RS4I.rs","timestamp":1708528440405},{"id":"5o6U.rs","source":"undoRedo.source","timestamp":1708528464932},{"id":"8Y2N.rs","timestamp":1708528468975},{"id":"d7tc.rs","timestamp":1708528756204},{"id":"kEZ6.rs","timestamp":1708528774024},{"id":"i3Tl.rs","timestamp":1708528790257},{"id":"xS7s.rs","timestamp":1708528814177},{"id":"CW8Z.rs","source":"undoRedo.source","timestamp":1708528819817},{"id":"faMa.rs","timestamp":1708528821821},{"id":"bY2y.rs","timestamp":1708528832151},{"id":"wmjB.rs","timestamp":1708528856567},{"id":"2gQC.rs","timestamp":1708529475436},{"id":"UA7H.rs","source":"undoRedo.source","timestamp":1708529493559},{"id":"v16o.rs","timestamp":1708529510219},{"id":"7Lwo.rs","timestamp":1708529523546},{"id":"FxNM.rs","timestamp":1708529569473},{"id":"Fp38.rs","timestamp":1708529609799},{"id":"9R6R.rs","timestamp":1708529735599},{"id":"7m8K.rs","timestamp":1708530568415},{"id":"31Fg.rs","timestamp":1708530593621},{"id":"z2uD.rs","timestamp":1708531438195},{"id":"nxlB.rs","timestamp":1708531476475},{"id":"ABb7.rs","timestamp":1708531968526},{"id":"fV2A.rs","timestamp":1708531997509},{"id":"2LYF.rs","timestamp":1708532024599},{"id":"yPvK.rs","timestamp":1708532466057},{"id":"AwdA.rs","timestamp":1708532497420},{"id":"pyqa.rs","timestamp":1708534990695},{"id":"ogIp.rs","timestamp":1708535360949},{"id":"ScZY.rs","timestamp":1708535383195}]}